pytest_relay/__init__.py
pytest_relay/plugin.py
pytest_relay/py.typed
pytest_relay/model/__init__.py
pytest_relay/model/common.py
pytest_relay/model/list.py
pytest_relay/model/observer.py
pytest_relay/model/record.py
pytest_relay/model/session.py
pytest_relay/model/testcase.py
pytest_relay/plugger/__init__.py
pytest_relay/plugger/plugin.py
pytest_relay-0.0.1.dist-info/METADATA
pytest_relay-0.0.1.dist-info/WHEEL
pytest_relay-0.0.1.dist-info/entry_points.txt
pytest_relay-0.0.1.dist-info/licenses/COPYING
pytest_relay-0.0.1.dist-info/RECORD
